jsonapi_requests/__init__.py
jsonapi_requests/auth.py
jsonapi_requests/base.py
jsonapi_requests/configuration.py
jsonapi_requests/data.py
jsonapi_requests/request_factory.py
jsonapi_requests/orm/__init__.py
jsonapi_requests/orm/api.py
jsonapi_requests/orm/api_model.py
jsonapi_requests/orm/fields.py
jsonapi_requests/orm/registry.py
jsonapi_requests/orm/repositories.py
jsonapi_requests-0.8.0.dist-info/AUTHORS
jsonapi_requests-0.8.0.dist-info/LICENSE
jsonapi_requests-0.8.0.dist-info/METADATA
jsonapi_requests-0.8.0.dist-info/WHEEL
jsonapi_requests-0.8.0.dist-info/top_level.txt
jsonapi_requests-0.8.0.dist-info/RECORD
