Metadata-Version: 2.1
Name: jsonapi-requests
Version: 0.8.0
Summary: Python client implementation for json api. http://jsonapi.org/
Home-page: https://github.com/socialwifi/jsonapi-requests
Author: Social WiFi
Author-email: it@socialwifi.com
License: BSD
Classifier: Development Status :: 5 - Production/Stable
Classifier: Environment :: Console
Classifier: Intended Audience :: Developers
Classifier: License :: OSI Approved :: BSD License
Classifier: Operating System :: OS Independent
Classifier: Programming Language :: Python
Classifier: Programming Language :: Python :: 3
Classifier: Programming Language :: Python :: 3.9
Classifier: Programming Language :: Python :: 3.10
Classifier: Programming Language :: Python :: 3.11
Classifier: Programming Language :: Python :: 3.12
Requires-Python: >=3.9
License-File: LICENSE
License-File: AUTHORS
Requires-Dist: requests
Requires-Dist: tenacity
Provides-Extra: flask
Requires-Dist: flask ; extra == 'flask'
